certwiz/__init__.py
certwiz/main.py
certwiz/normal_use.py
certwiz-0.1.0.dist-info/METADATA
certwiz-0.1.0.dist-info/WHEEL
certwiz-0.1.0.dist-info/top_level.txt
certwiz-0.1.0.dist-info/RECORD
