Metadata-Version: 2.1
Name: certwiz
Version: 0.1.0
Summary: Quickly add SSL functionality into a microservice
Home-page: https://github.com/manbehindthemadness/certwiz
Author: Manbehindthemadness
Author-email: manbehindthemadness@gmail.com
Classifier: Programming Language :: Python :: 3
Classifier: License :: OSI Approved :: MIT License
Classifier: Operating System :: OS Independent
Requires-Python: >=3.6
Requires-Dist: pyOpenSSL
Requires-Dist: build-settings
